ib/__init__.py
ib/version.py
ib/ext/AnyWrapper.py
ib/ext/AnyWrapperMsgGenerator.py
ib/ext/ComboLeg.py
ib/ext/CommissionReport.py
ib/ext/Contract.py
ib/ext/ContractDetails.py
ib/ext/EClientErrors.py
ib/ext/EClientSocket.py
ib/ext/EReader.py
ib/ext/EWrapper.py
ib/ext/EWrapperMsgGenerator.py
ib/ext/Execution.py
ib/ext/ExecutionFilter.py
ib/ext/MarketDataType.py
ib/ext/Order.py
ib/ext/OrderComboLeg.py
ib/ext/OrderState.py
ib/ext/ScannerSubscription.py
ib/ext/TagValue.py
ib/ext/TickType.py
ib/ext/UnderComp.py
ib/ext/Util.py
ib/ext/__init__.py
ib/lib/__init__.py
ib/lib/logger.py
ib/lib/overloading.py
ib/opt/__init__.py
ib/opt/connection.py
ib/opt/dispatcher.py
ib/opt/message.py
ib/opt/messagetools.py
ib/opt/receiver.py
ib/opt/sender.py
ib/sym/__init__.py
IbPy_lucidinvestor-1.0.3.dist-info/LICENSE
IbPy_lucidinvestor-1.0.3.dist-info/METADATA
IbPy_lucidinvestor-1.0.3.dist-info/WHEEL
IbPy_lucidinvestor-1.0.3.dist-info/top_level.txt
IbPy_lucidinvestor-1.0.3.dist-info/RECORD
