Metadata-Version: 2.1
Name: IbPy-lucidinvestor
Version: 1.0.3
Summary: Interactive Brokers Python API (python 3 compatible version of https://github.com/blampe/IbPy) - maintained by LucidInvestor
Home-page: https://gitlab.com/algorithmic-trading-library/IbPy3
Author: maintainer: LucidInvestor
Author-email: info@lucidinvestor.ca
License: BSD
Download-URL: https://gitlab.com/algorithmic-trading-library/IbPy3/-/archive/1.0.3/IbPy3-1.0.3.tar.gz
Keywords: trading,development
Platform: UNKNOWN
Classifier: Development Status :: 5 - Production/Stable
Classifier: Intended Audience :: Developers
Classifier: Intended Audience :: Financial and Insurance Industry
Classifier: Topic :: Office/Business :: Financial
Classifier: Topic :: Office/Business :: Financial :: Investment
Classifier: Topic :: Scientific/Engineering :: Interface Engine/Protocol Translator
Classifier: Topic :: Software Development :: Libraries
Classifier: Topic :: Software Development :: Libraries :: Python Modules
Classifier: License :: OSI Approved :: BSD License
Classifier: Programming Language :: Python :: 3
Classifier: Programming Language :: Python :: 3.2
Classifier: Programming Language :: Python :: 3.3
Classifier: Programming Language :: Python :: 3.4
Classifier: Programming Language :: Python :: 3.5
Classifier: Programming Language :: Python :: 3.6
Classifier: Programming Language :: Python :: 3.8
Classifier: Operating System :: OS Independent
License-File: LICENSE
